{
    "name": "Send daily Google Ads performance stats to Slack",
    "flow": [
        {
            "id": 8,
            "module": "util:SetVariables",
            "version": 1,
            "parameters": {},
            "mapper": {
                "scope": "roundtrip",
                "variables": [
                    {
                        "name": "customer_id",
                        "value": ""
                    },
                    {
                        "name": "period",
                        "value": "YESTERDAY"
                    }
                ]
            },
            "metadata": {
                "designer": {
                    "x": 0,
                    "y": 0
                },
                "restore": {
                    "expect": {
                        "scope": {
                            "label": "One cycle"
                        },
                        "variables": {
                            "items": [
                                null,
                                null
                            ]
                        }
                    }
                },
                "expect": [
                    {
                        "name": "variables",
                        "spec": [
                            {
                                "name": "name",
                                "type": "text",
                                "label": "Variable name",
                                "required": true
                            },
                            {
                                "name": "value",
                                "type": "any",
                                "label": "Variable value"
                            }
                        ],
                        "type": "array",
                        "label": "Variables"
                    },
                    {
                        "name": "scope",
                        "type": "select",
                        "label": "Variable lifetime",
                        "required": true,
                        "validate": {
                            "enum": [
                                "roundtrip",
                                "execution"
                            ]
                        }
                    }
                ],
                "interface": [
                    {
                        "name": "customer_id",
                        "type": "any",
                        "label": "customer_id"
                    },
                    {
                        "name": "period",
                        "type": "any",
                        "label": "period"
                    }
                ]
            }
        },
        {
            "id": 2,
            "module": "google-ads-campaign-management:getAnAccount",
            "version": 1,
            "parameters": {},
            "filter": {
                "name": "config exists",
                "conditions": [
                    [
                        {
                            "a": "{{average(8.customer_id)}}",
                            "b": "0",
                            "o": "number:greater"
                        },
                        {
                            "a": "{{8.period}}",
                            "o": "exist"
                        }
                    ]
                ]
            },
            "mapper": {
                "account": "{{8.customer_id}}"
            },
            "metadata": {
                "designer": {
                    "x": 300,
                    "y": 0
                },
                "restore": {
                    "expect": {
                        "account": {
                            "mode": "edit"
                        }
                    },
                    "parameters": {
                        "__IMTCONN__": {
                            "data": {
                                "scoped": "true",
                                "connection": "google-ads2"
                            },
                            "label": "My Google Ads connection"
                        }
                    }
                },
                "parameters": [
                    {
                        "name": "__IMTCONN__",
                        "type": "account:google-ads2",
                        "label": "Connection"
                    }
                ],
                "expect": [
                    {
                        "mode": "edit",
                        "name": "account",
                        "type": "select",
                        "label": "Account/Customer ID",
                        "required": true
                    }
                ]
            }
        },
        {
            "id": 3,
            "module": "google-ads-campaign-management:makeApiCall",
            "version": 1,
            "parameters": {},
            "filter": {
                "name": "account retrieved",
                "conditions": [
                    [
                        {
                            "a": "{{2.id}}",
                            "b": "",
                            "o": "exist"
                        }
                    ]
                ]
            },
            "mapper": {
                "url": "/v9/customers/{{8.customer_id}}/googleAds:searchStream",
                "body": "{\"query\":\n\t\"SELECT campaign.name, metrics.impressions, metrics.clicks, metrics.cost_micros, metrics.conversions, metrics.conversions_value, metrics.cost_per_conversion, metrics.ctr\n\tFROM campaign\n\tWHERE segments.date DURING {{8.period}} AND metrics.cost_micros>0\n\tORDER BY metrics.cost_micros DESC\"\n}",
                "method": "POST",
                "headers": [
                    {
                        "key": "Content-Type",
                        "value": "application/json"
                    }
                ]
            },
            "metadata": {
                "designer": {
                    "x": 600,
                    "y": 0
                },
                "restore": {
                    "expect": {
                        "qs": {
                            "mode": "chose"
                        },
                        "method": {
                            "mode": "chose",
                            "label": "POST"
                        },
                        "headers": {
                            "mode": "chose",
                            "items": [
                                null
                            ]
                        }
                    },
                    "parameters": {
                        "__IMTCONN__": {
                            "data": {
                                "scoped": "true",
                                "connection": "google-ads2"
                            },
                            "label": "My Google Ads connection"
                        }
                    }
                },
                "parameters": [
                    {
                        "name": "__IMTCONN__",
                        "type": "account:google-ads2",
                        "label": "Connection"
                    }
                ],
                "expect": [
                    {
                        "name": "url",
                        "type": "text",
                        "label": "URL",
                        "required": true
                    },
                    {
                        "name": "method",
                        "type": "select",
                        "label": "Method",
                        "required": true,
                        "validate": {
                            "enum": [
                                "GET",
                                "POST",
                                "PUT",
                                "PATCH",
                                "DELETE"
                            ]
                        }
                    },
                    {
                        "name": "headers",
                        "spec": [
                            {
                                "name": "key",
                                "type": "text",
                                "label": "Key"
                            },
                            {
                                "name": "value",
                                "type": "text",
                                "label": "Value"
                            }
                        ],
                        "type": "array",
                        "label": "Headers"
                    },
                    {
                        "name": "qs",
                        "spec": [
                            {
                                "name": "key",
                                "type": "text",
                                "label": "Key"
                            },
                            {
                                "name": "value",
                                "type": "text",
                                "label": "Value"
                            }
                        ],
                        "type": "array",
                        "label": "Query String"
                    },
                    {
                        "name": "body",
                        "type": "any",
                        "label": "Body"
                    }
                ]
            }
        },
        {
            "id": 4,
            "module": "builtin:BasicFeeder",
            "version": 1,
            "parameters": {},
            "filter": {
                "name": "campaigns found",
                "conditions": [
                    [
                        {
                            "a": "{{3.body[].results}}",
                            "b": "0",
                            "o": "array:greater"
                        }
                    ]
                ]
            },
            "mapper": {
                "array": "{{3.body[].results}}"
            },
            "metadata": {
                "designer": {
                    "x": 900,
                    "y": 0
                },
                "restore": {
                    "array": {
                        "mode": "edit"
                    }
                },
                "expect": [
                    {
                        "mode": "edit",
                        "name": "array",
                        "spec": [],
                        "type": "array",
                        "label": "Array"
                    }
                ]
            }
        },
        {
            "id": 5,
            "module": "util:TextAggregator",
            "version": 1,
            "parameters": {
                "feeder": 3,
                "rowSeparator": ""
            },
            "mapper": {
                "value": "Campaign Name - {{4.campaign.name}}\nImpressions - {{4.metrics.impressions}}\nClicks - {{4.metrics.clicks}}\nCost - {{(4.metrics.costMicros / 1000000)}}\nConversions - {{4.metrics.conversions}}\nConversion Value - {{4.metrics.conversionsValue}}\nCost per Conversion - {{4.metrics.costPerConversion}}"
            },
            "metadata": {
                "designer": {
                    "x": 1200,
                    "y": 0
                },
                "restore": {
                    "extra": {
                        "feeder": {
                            "label": "Google Ads Campaign Management - Make an API Call [3]"
                        }
                    },
                    "parameters": {
                        "rowSeparator": {
                            "label": "Empty"
                        }
                    }
                },
                "parameters": [
                    {
                        "name": "rowSeparator",
                        "type": "select",
                        "label": "Row separator",
                        "validate": {
                            "enum": [
                                "\n",
                                "\t",
                                "other"
                            ]
                        }
                    }
                ],
                "expect": [
                    {
                        "name": "value",
                        "type": "text",
                        "label": "Text"
                    }
                ],
                "advanced": true
            },
            "flags": {
                "stopIfEmpty": true
            }
        },
        {
            "id": 7,
            "module": "slack:CreateMessage",
            "version": 4,
            "parameters": {},
            "mapper": {
                "text": "Hey! \nHere's the latest Google Ads report:\n\n{{5.text}}",
                "parse": false,
                "mrkdwn": true,
                "channel": "DM4UHB7HT",
                "channelType": "im",
                "channelWType": "list"
            },
            "metadata": {
                "designer": {
                    "x": 1500,
                    "y": 0
                },
                "restore": {
                    "expect": {
                        "parse": {
                            "mode": "chose"
                        },
                        "mrkdwn": {
                            "mode": "chose"
                        },
                        "channel": {
                            "mode": "chose",
                            "label": "l.govender"
                        },
                        "link_names": {
                            "mode": "chose"
                        },
                        "channelType": {
                            "label": "IM channel"
                        },
                        "channelWType": {
                            "label": "Select from the list"
                        },
                        "unfurl_links": {
                            "mode": "chose"
                        },
                        "unfurl_media": {
                            "mode": "chose"
                        },
                        "reply_broadcast": {
                            "mode": "chose"
                        }
                    },
                    "parameters": {
                        "__IMTCONN__": {
                            "data": {
                                "scoped": "true",
                                "connection": "slack2"
                            },
                            "label": "My Slack (user) connection (lwgovender7)"
                        }
                    }
                },
                "parameters": [
                    {
                        "name": "__IMTCONN__",
                        "type": "account:slack2,slack3",
                        "label": "Connection"
                    }
                ],
                "expect": [
                    {
                        "name": "channelWType",
                        "type": "select",
                        "label": "Enter a channel ID or name",
                        "required": true,
                        "validate": {
                            "enum": [
                                "manualy",
                                "list"
                            ]
                        }
                    },
                    {
                        "name": "text",
                        "type": "text",
                        "label": "Text"
                    },
                    {
                        "name": "blocks",
                        "type": "text",
                        "label": "Blocks"
                    },
                    {
                        "name": "thread_ts",
                        "type": "text",
                        "label": "Thread message ID (time stamp)"
                    },
                    {
                        "name": "reply_broadcast",
                        "type": "boolean",
                        "label": "Reply broadcast"
                    },
                    {
                        "name": "link_names",
                        "type": "boolean",
                        "label": "Link names"
                    },
                    {
                        "name": "parse",
                        "type": "boolean",
                        "label": "Parse message text"
                    },
                    {
                        "name": "mrkdwn",
                        "type": "boolean",
                        "label": "Use markdown"
                    },
                    {
                        "name": "unfurl_links",
                        "type": "boolean",
                        "label": "Unfurl primarily text-based content"
                    },
                    {
                        "name": "unfurl_media",
                        "type": "boolean",
                        "label": "Unfurl media content"
                    },
                    {
                        "name": "icon_emoji",
                        "type": "text",
                        "label": "Icon emoji"
                    },
                    {
                        "name": "icon_url",
                        "type": "url",
                        "label": "Icon url"
                    },
                    {
                        "name": "username",
                        "type": "text",
                        "label": "User name"
                    },
                    {
                        "name": "channelType",
                        "type": "select",
                        "label": "Channel type",
                        "required": true,
                        "validate": {
                            "enum": [
                                "public",
                                "private",
                                "im",
                                "mpim"
                            ]
                        }
                    },
                    {
                        "name": "channel",
                        "type": "select",
                        "label": "User",
                        "required": true
                    }
                ]
            }
        }
    ],
    "metadata": {
        "instant": false,
        "version": 1,
        "scenario": {
            "roundtrips": 1,
            "maxErrors": 3,
            "autoCommit": true,
            "autoCommitTriggerLast": true,
            "sequential": false,
            "slots": null,
            "confidential": false,
            "dataloss": false,
            "dlq": false,
            "freshVariables": false
        },
        "designer": {
            "orphans": []
        },
        "zone": "eu1.make.com",
        "notes": []
    }
}